setup.py
speca/__init__.py
speca/parser.py
speca.egg-info/PKG-INFO
speca.egg-info/SOURCES.txt
speca.egg-info/dependency_links.txt
speca.egg-info/entry_points.txt
speca.egg-info/not-zip-safe
speca.egg-info/top_level.txt
speca/commands/__init__.py
speca/commands/parse.py
speca/lang/__init__.py
speca/lang/erlang/__init__.py
speca/lang/erlang/generator.py
speca/lang/javascript/__init__.py
speca/lang/javascript/generator.py
speca/lang/python/__init__.py
speca/lang/python/generator.py