Metadata-Version: 1.0
Name: speca
Version: 0.2.2
Summary: Python generator of templates for projects
Home-page: UNKNOWN
Author: selead
Author-email: allselead@gmail.com
License: GPLv2
Platform: UNKNOWN
